open_corpus_co_es/__init__.py
open_corpus_co_es/__main__.py
open_corpus_co_es/catalog.json
open_corpus_co_es/downloader.py
open_corpus_co_es/loader.py
open_corpus_co_es/utils.py
open_corpus_co_es-0.1.0.dist-info/licenses/LICENSE
open_corpus_co_es-0.1.0.dist-info/METADATA
open_corpus_co_es-0.1.0.dist-info/WHEEL
open_corpus_co_es-0.1.0.dist-info/top_level.txt
open_corpus_co_es-0.1.0.dist-info/RECORD
