Metadata-Version: 2.4
Name: open_corpus_co_es
Version: 0.1.0
Summary: Corpus en español de Colombia para procesamiento de lenguaje natural
Author: Luis Gabriel Moreno Sandoval
Author-email: Luis Gabriel Moreno Sandoval <morenoluis@javeriana.edu.co>
License: MIT
Requires-Python: >=3.6
License-File: LICENSE
Requires-Dist: nltk
Requires-Dist: pandas
Requires-Dist: gdown
Requires-Dist: pyarrow
Requires-Dist: fastparquet
Requires-Dist: tqdm
Dynamic: author
Dynamic: license-file
Dynamic: requires-python
